Metadata-Version: 2.1
Name: phraseextractor
Version: 0.5
Summary: A shallow phrase extractor
Home-page: https://github.com/ppengkkang/phrase-extractor
Author: Peng Yong
Author-email: ppengkkang16@gmail.com
License: MIT
Platform: UNKNOWN
Classifier: Programming Language :: Python :: 3
Classifier: Operating System :: OS Independent
